tmdb_client/__init__.py
tmdb_client/api_client.py
tmdb_client/api_response.py
tmdb_client/configuration.py
tmdb_client/exceptions.py
tmdb_client/py.typed
tmdb_client/rest.py
tmdb_client/api/__init__.py
tmdb_client/api/default_api.py
tmdb_client/models/__init__.py
tmdb_client/models/account_details200_response.py
tmdb_client/models/account_details200_response_avatar.py
tmdb_client/models/account_details200_response_avatar_gravatar.py
tmdb_client/models/account_details200_response_avatar_tmdb.py
tmdb_client/models/account_favorite_tv200_response.py
tmdb_client/models/account_favorite_tv200_response_results_inner.py
tmdb_client/models/account_get_favorites200_response.py
tmdb_client/models/account_get_favorites200_response_results_inner.py
tmdb_client/models/account_lists200_response.py
tmdb_client/models/account_lists200_response_results_inner.py
tmdb_client/models/account_rated_movies200_response.py
tmdb_client/models/account_rated_movies200_response_results_inner.py
tmdb_client/models/account_rated_tv200_response.py
tmdb_client/models/account_rated_tv200_response_results_inner.py
tmdb_client/models/account_rated_tv_episodes200_response.py
tmdb_client/models/account_rated_tv_episodes200_response_results_inner.py
tmdb_client/models/account_watchlist_movies200_response.py
tmdb_client/models/account_watchlist_movies200_response_results_inner.py
tmdb_client/models/account_watchlist_tv200_response.py
tmdb_client/models/account_watchlist_tv200_response_results_inner.py
tmdb_client/models/alternative_names_copy200_response.py
tmdb_client/models/alternative_names_copy200_response_logos_inner.py
tmdb_client/models/authentication_create_guest_session200_response.py
tmdb_client/models/authentication_create_request_token200_response.py
tmdb_client/models/authentication_create_session200_response.py
tmdb_client/models/authentication_create_session_from_login200_response.py
tmdb_client/models/authentication_create_session_from_v4_token200_response.py
tmdb_client-0.0.1.dist-info/LICENSE
tmdb_client-0.0.1.dist-info/METADATA
tmdb_client-0.0.1.dist-info/WHEEL
tmdb_client-0.0.1.dist-info/top_level.txt
tmdb_client-0.0.1.dist-info/RECORD
